zymod/__init__.py
zymod/zymod.py
zymod/zymod_config.py
zymod/event/__init__.py
zymod/event/zy_event_level_enum.py
zymod/event/zy_internal_event.py
zymod/inotify/__init__.py
zymod/inotify/zy_file_event_enum.py
zymod/inotify/zy_inotify_file_event.py
zymod/ssl/__init__.py
zymod/ssl/zy_cert.py
zymod/ssl/zy_cert_validator.py
zymod/systemd/__init__.py
zymod/systemd/zy_systemd_manager.py
zymod/systemd/zy_systemd_service.py
zymod/systemd/zy_systemd_service_prop.py
zymod/systemd/zy_systemd_timer.py
zymod/systemd/zy_systemd_timer_prop.py
zymod/systemd/zy_systemd_unit.py
zymod/systemd/zy_systemd_unit_prop.py
zymod/util/__init__.py
zymod/util/dbus_utils.py
zymod/util/time_duration_calculator.py
zymod/zyapp_service/__init__.py
zymod/zyapp_service/service.py
zymod/zyprocfs/__init__.py
zymod/zyprocfs/procfs.py
zymod_help/version.txt
zymod-0.0.2.3.dist-info/LICENSE
zymod-0.0.2.3.dist-info/METADATA
zymod-0.0.2.3.dist-info/WHEEL
zymod-0.0.2.3.dist-info/top_level.txt
zymod-0.0.2.3.dist-info/RECORD
