Metadata-Version: 2.1
Name: zymod
Version: 0.0.2.3
Summary: ZhiYan Python SDK
Home-page: https://gitee.com/warp-drive-tech/libzymod-python
Author: Chengdu Geek Camp
Author-email: lq@cdgeekcamp.com
License: MIT
Platform: any
Classifier: Intended Audience :: Developers
Classifier: License :: OSI Approved :: MIT License
Classifier: Operating System :: OS Independent
Classifier: Programming Language :: Python
Classifier: Programming Language :: Python :: 3
Classifier: Topic :: Software Development :: Libraries :: Python Modules
License-File: LICENSE
Requires-Dist: grpcio-tools
Requires-Dist: setuptools
Requires-Dist: happy-python
Requires-Dist: wheel
Requires-Dist: zygrpc
Requires-Dist: cryptography
Requires-Dist: pyinotify
Requires-Dist: meson
Requires-Dist: ninja
Requires-Dist: psutil
Requires-Dist: dbus-python
